{
  "events": [
    {
      "event_date": null,
      "event_name": "Datathon 2022",
      "event_photo_url": "",
      "event_purpose": "Conseguir la mayor participaci\u00f3n posible en los seminarios de formaci\u00f3n y en la competici\u00f3n",
      "event_report_url": "",
      "event_tweet_url": "",
      "event_video_url": "",
      "has_event_report": false,
      "latitude": 38.43873,
      "longitude": -0.5428,
      "num_participants": "300",
      "online_event_url": "",
      "organisers": "Direcci\u00f3n General  General de Transparencia, Atenci\u00f3n a la Ciudadan\u00eda y Buen Gobierno, Universitat Polit\u00e8cnica de Val\u00e8ncia, Universidad de Alicante, Universidad Miguel Hern\u00e1ndez, ",
      "place": "Alicante",
      "slug": "datathon-2022",
      "url": "https://www.ctranspa.webs.upv.es/datathon-2022/",
      "world_region_code": "",
      "world_region_text": ""
    },
    {
      "event_date": null,
      "event_name": "Datathon 2022 Valencia",
      "event_photo_url": "",
      "event_purpose": "Esperamos conseguir la m\u00e1s amplia participaci\u00f3n para la competici\u00f3n",
      "event_report_url": "",
      "event_tweet_url": "",
      "event_video_url": "",
      "has_event_report": false,
      "latitude": 38.43873,
      "longitude": -0.5428,
      "num_participants": "300",
      "online_event_url": "",
      "organisers": "Universidad de Alicante, Universitat Polit\u00e8cnica de Val\u00e8ncia, Universitat de Val\u00e8ncia, Universidad Miguel Hern\u00e1ndez",
      "place": "Alicante, Valencia",
      "slug": "datathon-2022-valencia",
      "url": "https://www.ctranspa.webs.upv.es/datathon-2022/",
      "world_region_code": "",
      "world_region_text": ""
    },
    {
      "event_date": null,
      "event_name": "Datenspaziergang Wien / Data walk Vienna",
      "event_photo_url": "",
      "event_purpose": "We want to make Open Data visible.",
      "event_report_url": "",
      "event_tweet_url": "",
      "event_video_url": "",
      "has_event_report": false,
      "latitude": 48.20872,
      "longitude": 16.38632,
      "num_participants": "50",
      "online_event_url": "",
      "organisers": "City of Vienna ",
      "place": "Vienna",
      "slug": "datenspaziergang-wien-data-walk-vienna",
      "url": "https://digitales.wien.gv.at/open-data-days-2022/",
      "world_region_code": "",
      "world_region_text": ""
    },
    {
      "event_date": null,
      "event_name": "Dein Tag mit Daten",
      "event_photo_url": "",
      "event_purpose": "Make people aware of existing open data. Develop data stories with participants",
      "event_report_url": "",
      "event_tweet_url": "",
      "event_video_url": "",
      "has_event_report": false,
      "latitude": 49.00809,
      "longitude": 8.40376,
      "num_participants": "30",
      "online_event_url": "",
      "organisers": "OK Lab Karlsruhe",
      "place": "Karlsruhe",
      "slug": "dein-tag-mit-daten",
      "url": "https://ok-lab-karlsruhe.de/projekte/odd22/",
      "world_region_code": "",
      "world_region_text": ""
    },
    {
      "event_date": null,
      "event_name": "D\u00eda de Datos Abiertos 2022 en M\u00e9rida, Yucat\u00e1n.",
      "event_photo_url": "",
      "event_purpose": "Difundir el uso de los datos abiertos entre ciudadan\u00eda, instituciones p\u00fablicas y sector privado.",
      "event_report_url": "",
      "event_tweet_url": "",
      "event_video_url": "",
      "has_event_report": false,
      "latitude": 20.967779,
      "longitude": -89.62426,
      "num_participants": "30",
      "online_event_url": "",
      "organisers": "Laboratorio de Pol\u00edticas para la Seguridad y el Desarrollo",
      "place": "M\u00e9rida, Yucat\u00e1n",
      "slug": "dia-de-datos-abiertos-2022-en-merida-yucatan",
      "url": "https://seguridadydesarrollo.org/open-data-day",
      "world_region_code": "",
      "world_region_text": ""
    },
    {
      "event_date": null,
      "event_name": "Mapeando el barrio Nicol\u00e1s de Federm\u00e1n de Bogot\u00e1",
      "event_photo_url": "",
      "event_purpose": "To add details in the map, such as addresses or business, with the community while teaching OpenData",
      "event_report_url": "",
      "event_tweet_url": "",
      "event_video_url": "",
      "has_event_report": false,
      "latitude": 4.646987,
      "longitude": -74.082394,
      "num_participants": "25",
      "online_event_url": "",
      "organisers": "Andres Gomez, MaptimeBogota",
      "place": "Bogota",
      "slug": "mapeando-el-barrio-nicolas-de-federman-de-bogota",
      "url": "https://www.meetup.com/maptime-bogota-colombia-osm/events/283295807/",
      "world_region_code": "",
      "world_region_text": ""
    },
    {
      "event_date": null,
      "event_name": "Open Data Day Paraguay",
      "event_photo_url": "",
      "event_purpose": "Show the new projects related to Open Data and Transparency",
      "event_report_url": "",
      "event_tweet_url": "",
      "event_video_url": "",
      "has_event_report": false,
      "latitude": -25.298428,
      "longitude": -57.581896,
      "num_participants": "30",
      "online_event_url": "",
      "organisers": "Civilab",
      "place": "Asuncion",
      "slug": "open-data-day-paraguay",
      "url": "https://civilab.org.py/",
      "world_region_code": "",
      "world_region_text": ""
    },
    {
      "event_date": null,
      "event_name": "Open Data Day Santos 2022 - Py013",
      "event_photo_url": "",
      "event_purpose": "Data Exploration and Data Mapping",
      "event_report_url": "",
      "event_tweet_url": "",
      "event_video_url": "",
      "has_event_report": false,
      "latitude": -23.956289,
      "longitude": -46.326462,
      "num_participants": "25",
      "online_event_url": "",
      "organisers": "Py013",
      "place": "Santos, SP - Brasil",
      "slug": "open-data-day-santos-2022-py013",
      "url": "https://forms.gle/yc1Q2RRpmzh3R7zCA",
      "world_region_code": "",
      "world_region_text": ""
    }
  ]
}